LICENSE.txt
MANIFEST.in
README.rst
setup.cfg
setup.py
blade/__init__.py
blade/xcmp.py
blade/xfilter.py
blade/xmap.py
blade/xmath.py
blade/xreduce.py
blade/xslice.py
blade.egg-info/PKG-INFO
blade.egg-info/SOURCES.txt
blade.egg-info/dependency_links.txt
blade.egg-info/not-zip-safe
blade.egg-info/requires.txt
blade.egg-info/top_level.txt
reqs/requires.txt
tests/__init__.py
tests/test_xcmp.py
tests/test_xfilter.py
tests/test_xmap.py
tests/test_xmath.py
tests/test_xreduce.py
tests/test_xslice.py